devopipe/__init__.py
devopipe/src/downloaded_template.yaml
devopipe/src/main.py
devopipe/src/runnable/terraform/aws/main.tf
devopipe/src/setup_template.yaml
devopipe/src/templates/IaC/aws/argocd/argocd.yaml
devopipe/src/templates/IaC/aws/argocd/git-repo-secret.yaml
devopipe/src/templates/IaC/aws/blueprints.tf
devopipe/src/templates/IaC/aws/create-namespace.yaml
devopipe/src/templates/IaC/aws/create-vcluster.yaml
devopipe/src/templates/IaC/aws/developer-role.tf
devopipe/src/templates/IaC/aws/kubernetes-addons.tf
devopipe/src/templates/IaC/aws/main.tf
devopipe/src/templates/IaC/aws/values/argocd.yaml
devopipe/src/templates/IaC/aws/values/vcluster-config-init.yaml
devopipe/src/templates/IaC/aws/variables.tf
devopipe/src/templates/IaC/aws/vpc-module.tf
devopipe/src/templates/ci-pipeline/azure-pipelines.yaml
devopipe/src/templates/ci-pipeline/deploy-artifacts-docker-hub.yaml
devopipe/src/templates/ci-pipeline/deploy-artifacts-ecr.yaml
devopipe/src/templates/ci-pipeline/get-artifact.yaml
devopipe/src/templates/ci-pipeline/set-artifact.yaml
devopipe/src/templates/kubernetes/apps/deployment.yaml
devopipe/src/templates/kubernetes/apps/deployment_backend.yaml
devopipe/src/templates/kubernetes/apps/deployment_database.yaml
devopipe/src/templates/kubernetes/apps/pgadmin-deploy.yaml
devopipe/src/templates/kubernetes/apps/pgadmin-secret.yaml
devopipe/src/templates/kubernetes/aws/ingress_aws.yaml
devopipe/src/templates/kubernetes/aws/service-account.yaml
devopipe/src/templates/kubernetes/aws/storage.yaml
devopipe/src/templates/tests/database-sonarqube.yaml
devopipe/src/templates/tests/deployment-sonarqube.yaml
devopipe/src/templates/tests/storage_sonarqube.yaml
devopipe-0.1.7.dist-info/METADATA
devopipe-0.1.7.dist-info/WHEEL
devopipe-0.1.7.dist-info/entry_points.txt
devopipe-0.1.7.dist-info/RECORD
